caen_hv_py/CAENHVController.py
caen_hv_py/__init__.py
caen_hv_py/hv_c_lib/libhv_c.so
caen_hv_py/tests/__init__.py
caen_hv_py/tests/get_set_param_test.py
caen_hv_py/tests/power_test.py
caen_hv_py/tests/voltage_power_test.py
caen_hv_py-1.10.dist-info/METADATA
caen_hv_py-1.10.dist-info/WHEEL
caen_hv_py-1.10.dist-info/top_level.txt
caen_hv_py-1.10.dist-info/RECORD
