Metadata-Version: 2.1
Name: caen-hv-py
Version: 1.10
Summary: Python wrapper for CAEN High Voltage C library.
Home-page: https://github.com/Dyn0402/CAEN_HV_Python
Author: Dylan Neff
Author-email: dneff@ucla.edu
License: UNKNOWN
Platform: UNKNOWN
